Metadata-Version: 2.4
Name: albumentationsx
Version: 2.0.16
Summary: Fast, flexible, and advanced augmentation library for deep learning, computer vision, and medical imaging. Albumentations offers a wide range of transformations for both 2D (images, masks, bboxes, keypoints) and 3D (volumes, volumetric masks, keypoints) data, with optimized performance and seamless integration into ML workflows.
Author: Vladimir Iglovikov
Maintainer: Vladimir Iglovikov
License: AlbumentationsX Dual License Notice
Project-URL: Homepage, https://albumentations.ai
Keywords: 2D augmentation,3D augmentation,aerial photography,anomaly detection,artificial intelligence,autonomous driving,bounding boxes,classification,computer vision,computer vision library,data augmentation,data preprocessing,data science,deep learning,deep learning library,depth estimation,face recognition,fast augmentation,image augmentation,image processing,image transformation,images,instance segmentation,keras,keypoint detection,keypoints,machine learning,machine learning tools,masks,med
Classifier: Development Status :: 5 - Production/Stable
Classifier: Intended Audience :: Developers
Classifier: Intended Audience :: Healthcare Industry
Classifier: Intended Audience :: Information Technology
Classifier: Intended Audience :: Science/Research
Classifier: License :: OSI Approved :: GNU Affero General Public License v3 or later (AGPLv3+)
Classifier: Operating System :: OS Independent
Classifier: Programming Language :: Python
Classifier: Programming Language :: Python :: 3 :: Only
Classifier: Programming Language :: Python :: 3.10
Classifier: Programming Language :: Python :: 3.11
Classifier: Programming Language :: Python :: 3.12
Classifier: Programming Language :: Python :: 3.13
Classifier: Programming Language :: Python :: 3.14
Classifier: Topic :: Scientific/Engineering
Classifier: Topic :: Scientific/Engineering :: Artificial Intelligence
Classifier: Topic :: Scientific/Engineering :: Astronomy
Classifier: Topic :: Scientific/Engineering :: Atmospheric Science
Classifier: Topic :: Scientific/Engineering :: Bio-Informatics
Classifier: Topic :: Scientific/Engineering :: Image Processing
Classifier: Topic :: Scientific/Engineering :: Physics
Classifier: Topic :: Scientific/Engineering :: Visualization
Classifier: Topic :: Software Development :: Libraries
Classifier: Topic :: Software Development :: Libraries :: Python Modules
Classifier: Typing :: Typed
Requires-Python: >=3.10
License-File: LICENSE
Requires-Dist: albucore==0.0.36
Requires-Dist: numpy>=1.24.4
Requires-Dist: pydantic>=2.12.4
Requires-Dist: pyyaml
Requires-Dist: scipy>=1.10
Requires-Dist: typing-extensions>=4.9.0
Provides-Extra: contrib
Requires-Dist: opencv-contrib-python>=4.9.0.80; extra == "contrib"
Provides-Extra: contrib-headless
Requires-Dist: opencv-contrib-python-headless>=4.9.0.80; extra == "contrib-headless"
Provides-Extra: gui
Requires-Dist: opencv-python>=4.9.0.80; extra == "gui"
Provides-Extra: headless
Requires-Dist: opencv-python-headless>=4.9.0.80; extra == "headless"
Provides-Extra: hub
Requires-Dist: huggingface-hub; extra == "hub"
Provides-Extra: pillow
Requires-Dist: pillow; extra == "pillow"
Provides-Extra: pytorch
Requires-Dist: torch; extra == "pytorch"
Provides-Extra: pyvips
Requires-Dist: pyvips[binary]; extra == "pyvips"
Provides-Extra: text
Requires-Dist: pillow; extra == "text"
Dynamic: license-file
